dfimspect/__init__.py
dfimspect/_version.py
dfimspect/example.py
dfimspect/widget.py
dfimspect/static/extension.js
dfimspect/static/index.js
dfimspect/static/index.js.map
dfimspect-0.1.0a7.data/data/etc/jupyter/nbconfig/notebook.d/df-imspect-widget.json
dfimspect-0.1.0a7.data/data/share/jupyter/nbextensions/df-imspect-widget/extension.js
dfimspect-0.1.0a7.data/data/share/jupyter/nbextensions/df-imspect-widget/index.js
dfimspect-0.1.0a7.data/data/share/jupyter/nbextensions/df-imspect-widget/index.js.map
dfimspect-0.1.0a7.dist-info/LICENSE
dfimspect-0.1.0a7.dist-info/METADATA
dfimspect-0.1.0a7.dist-info/WHEEL
dfimspect-0.1.0a7.dist-info/top_level.txt
dfimspect-0.1.0a7.dist-info/RECORD
