Metadata-Version: 2.1
Name: dfimspect
Version: 0.1.0a7
Summary: Pandas DataFrame inspector for images with boxes
Home-page: https://github.com//df-imspect-widget
Author: Floris De Feyter
Author-email: floris.defeyter@kuleuven.be
License: UNKNOWN
Keywords: ipython,jupyter,widgets
Platform: UNKNOWN
Classifier: Development Status :: 4 - Beta
Classifier: Framework :: IPython
Classifier: Intended Audience :: Developers
Classifier: Intended Audience :: Science/Research
Classifier: Topic :: Multimedia :: Graphics
Classifier: Programming Language :: Python :: 2
Classifier: Programming Language :: Python :: 2.7
Classifier: Programming Language :: Python :: 3
Classifier: Programming Language :: Python :: 3.3
Classifier: Programming Language :: Python :: 3.4
Classifier: Programming Language :: Python :: 3.5
Requires-Dist: ipywidgets (>=7.0.0)
Requires-Dist: pandas
Requires-Dist: matplotlib
Requires-Dist: Pillow
Requires-Dist: scikit-video
Requires-Dist: tqdm
Requires-Dist: flutil
